jax_mda/__init__.py
jax_mda-0.0.1.dev0.dist-info/METADATA
jax_mda-0.0.1.dev0.dist-info/WHEEL
jax_mda-0.0.1.dev0.dist-info/RECORD
