Metadata-Version: 2.1
Name: jax-mda
Version: 0.0.1.dev0
Summary: JAX based molecular dynamic analysis tool.
Author: weihong.xu
Author-email: xuweihong.cn@gmail.com
Requires-Python: >=3.9,<4.0
Classifier: Programming Language :: Python :: 3
Classifier: Programming Language :: Python :: 3.9
Classifier: Programming Language :: Python :: 3.10
Classifier: Programming Language :: Python :: 3.11
Classifier: Programming Language :: Python :: 3.12
